pgn_speaker/__init__.py
pgn_speaker/__main__.py
pgn_speaker/cli.py
pgn_speaker/pyobjc_helper.py
pgn_speaker/winsdk_helper.py
pgn_speaker-1.1.0.dist-info/METADATA
pgn_speaker-1.1.0.dist-info/WHEEL
pgn_speaker-1.1.0.dist-info/entry_points.txt
pgn_speaker-1.1.0.dist-info/RECORD
