Metadata-Version: 2.4
Name: pgn-speaker
Version: 1.1.0
Summary: Reads moves one at a time from a PGN file for practicing chess visualization skills.
Project-URL: Repository, https://github.com/dlech/python-pgn-speaker
Author-email: David Lechner <david@lechnology.com>
License-Expression: MIT
Requires-Python: >=3.10
Requires-Dist: chess>=1.9.4
Requires-Dist: click>=8.1.3
Requires-Dist: pyobjc-framework-avfoundation>=9.0.1; sys_platform == 'darwin'
Requires-Dist: winrt-windows-foundation>=3.0.0; sys_platform == 'win32'
Requires-Dist: winrt-windows-media-playback>=3.0.0; sys_platform == 'win32'
Requires-Dist: winrt-windows-media-speechsynthesis>=3.0.0; sys_platform == 'win32'
Requires-Dist: winrt-windows-storage-streams>=3.0.0; sys_platform == 'win32'
